LICENSE
README.md
setup.cfg
setup.py
replize/__init__.py
replize/replize.py
replize.egg-info/PKG-INFO
replize.egg-info/SOURCES.txt
replize.egg-info/dependency_links.txt
replize.egg-info/entry_points.txt
replize.egg-info/not-zip-safe
replize.egg-info/top_level.txt