Metadata-Version: 2.1
Name: replize
Version: 0.1.4
Summary: Tools to create REPL interfaces
Home-page: https://github.com/i2mint/replize
License: apache-2.0
Keywords: REPL
License-File: LICENSE
